{
  "tableros": [
    {
      "nombre": "Por hacer",
      "tarjetas": [
        {
          "id": 1741651200001,
          "titulo": "Definir estructura del proyecto",
          "descripcion": "Crear carpetas, archivos base y configurar el entorno de desarrollo.",
          "prioridad": "Alta",
          "tag": "Setup",
          "estado": "Por hacer",
          "fecha_creacion": "2026-03-11",
          "fecha_inicio": "",
          "fecha_fin": "",
          "autor": "Pablo",
          "responsable": "Equipo"
        },
        {
          "id": 1741651200002,
          "titulo": "Diseñar modelo de datos",
          "descripcion": "Definir la estructura del archivo data.json con tableros y tarjetas.",
          "prioridad": "Alta",
          "tag": "Backend",
          "estado": "Por hacer",
          "fecha_creacion": "2026-03-11",
          "fecha_inicio": "",
          "fecha_fin": "",
          "autor": "Pablo",
          "responsable": "Pablo"
        },
        {
          "id": 1773202487624,
          "titulo": "Edición",
          "descripcion": "Editar Videos de Propuesta de Marketing",
          "prioridad": "Alta",
          "tag": "Backend",
          "estado": "Por hacer",
          "fecha_creacion": "2026-03-11",
          "fecha_inicio": "",
          "fecha_fin": "",
          "autor": "Marelly",
          "responsable": "Pablo Vergara"
        }
      ]
    },
    {
      "nombre": "En proceso",
      "tarjetas": [
        {
          "id": 1741651200003,
          "titulo": "Desarrollar vistas con Handlebars",
          "descripcion": "Crear las vistas home, login, register y dashboard con parciales.",
          "prioridad": "Alta",
          "tag": "Frontend",
          "estado": "En proceso",
          "fecha_creacion": "2026-03-11",
          "fecha_inicio": "2026-03-11",
          "fecha_fin": "",
          "autor": "Pablo",
          "responsable": "Equipo"
        }
      ]
    },
    {
      "nombre": "Visto bueno",
      "tarjetas": [
        {
          "id": 1741651200004,
          "titulo": "Revisar rutas GET y POST",
          "descripcion": "Verificar que todas las rutas respondan correctamente con datos reales.",
          "prioridad": "Media",
          "tag": "Backend",
          "estado": "Visto bueno",
          "fecha_creacion": "2026-03-11",
          "fecha_inicio": "2026-03-11",
          "fecha_fin": "2026-03-11",
          "autor": "Pablo",
          "responsable": "Pablo"
        }
      ]
    },
    {
      "nombre": "Hecho",
      "tarjetas": [
        {
          "id": 1741651200005,
          "titulo": "Instalar dependencias",
          "descripcion": "npm install express, hbs y nodemon correctamente configurados.",
          "prioridad": "Baja",
          "tag": "Setup",
          "estado": "Hecho",
          "fecha_creacion": "2026-03-10",
          "fecha_inicio": "2026-03-10",
          "fecha_fin": "2026-03-10",
          "autor": "Pablo",
          "responsable": "Pablo"
        }
      ]
    }
  ]
}